odoo/addons/ssi_service_operating_unit/README.rst
odoo/addons/ssi_service_operating_unit/__init__.py
odoo/addons/ssi_service_operating_unit/__manifest__.py
odoo/addons/ssi_service_operating_unit/models/__init__.py
odoo/addons/ssi_service_operating_unit/models/service_contract.py
odoo/addons/ssi_service_operating_unit/models/service_contract_fix_item_payment_term.py
odoo/addons/ssi_service_operating_unit/models/service_contract_fix_item_payment_term_detail.py
odoo/addons/ssi_service_operating_unit/security/ir_rule/service_contract.xml
odoo/addons/ssi_service_operating_unit/security/res_group/service_contract.xml
odoo/addons/ssi_service_operating_unit/static/description/icon.png
odoo/addons/ssi_service_operating_unit/views/service_contract_views.xml
odoo14_addon_ssi_service_operating_unit-14.0.1.0.1.dist-info/METADATA
odoo14_addon_ssi_service_operating_unit-14.0.1.0.1.dist-info/WHEEL
odoo14_addon_ssi_service_operating_unit-14.0.1.0.1.dist-info/top_level.txt
odoo14_addon_ssi_service_operating_unit-14.0.1.0.1.dist-info/RECORD
